{"dataset_name": "7hgn-sgmk", "columns": [{"column_name": "Organization", "number_non_empty_cells": 212, "number_empty_cells": 0, "number_distinct_values": 194, "frequent_values": ["Joyce Theater", "Museum of Chinese in America", "Elaine Kaufman Cultural Center", "Jacques Marchais Museum of Tibetan Art", "Brooklyn Historical Society"], "data_types": [{"type": "TEXT", "count": 212, "shortest_values": ["Roulette", "Dancewave", "Monuments", "ABC No Rio", "Film Forum"], "longest_values": ["Children's Museum of Manhattan Growth Through Art & Museum Experience Inc.", "New York State Theater / City Center for Music & Drama  (CIG)", "New York Live Arts (formerly Dance Theater Workshop)", "New York Shakespeare Festival / Public Theater (CIG)", "Bedford Stuyvesant Restoration Corporation (BSRC)"], "average_length": 25.5}]}, {"column_name": "Fiscal Year (FY)", "number_non_empty_cells": 212, "number_empty_cells": 0, "number_distinct_values": 2, "frequent_values": ["2018", "2019"], "data_types": [{"type": "INTEGER (LONG)", "count": 212, "max_value": 2019, "min_value": 2018, "mean": 2018.4433962264145, "stddev": 0.496785680969342}]}, {"column_name": " Borough President Funding", "number_non_empty_cells": 212, "number_empty_cells": 0, "number_distinct_values": 49, "frequent_values": ["0", "100000", "250000", "500000", "50000"], "data_types": [{"type": "INTEGER (LONG)", "count": 212, "max_value": 1600000, "min_value": 0, "mean": 177193.39622641527, "stddev": 274941.73542937875}]}, {"column_name": "City Council Funding", "number_non_empty_cells": 212, "number_empty_cells": 0, "number_distinct_values": 95, "frequent_values": ["None", "0", "100000", "250000", "300000"], "data_types": [{"type": "INTEGER (LONG)", "count": 180, "max_value": 8750000, "min_value": 0, "mean": 954577.777777778, "stddev": 1418505.2459682715}, {"type": "TEXT", "count": 32, "shortest_values": ["0", "None", "35000", "39000", "42000"], "longest_values": ["1000000", "1094000", "1100000", "1200000", "1223000"], "average_length": 35.59375}]}, {"column_name": "DCLA Funding", "number_non_empty_cells": 212, "number_empty_cells": 0, "number_distinct_values": 67, "frequent_values": ["None", "0", "500000", "2000000", "250000"], "data_types": [{"type": "INTEGER (LONG)", "count": 166, "max_value": 9000000, "min_value": 0, "mean": 1056487.9518072288, "stddev": 1665481.719590034}, {"type": "TEXT", "count": 46, "shortest_values": ["0", "None", "35000", "40000", "46000"], "longest_values": ["1000000", "1094000", "1100000", "1250000", "1300000"], "average_length": 22.47826086956522}]}, {"column_name": "Total Funding", "number_non_empty_cells": 212, "number_empty_cells": 0, "number_distinct_values": 151, "frequent_values": ["350000", "150000", "750000", "4500000", "250000"], "data_types": [{"type": "INTEGER (LONG)", "count": 212, "max_value": 17000000, "min_value": 0, "mean": 1814933.9622641508, "stddev": 2496301.064589962}]}], "key_column_candidates": []}