{"dataset_name": "NYCDCP Manhattan Bike Counts - Off Street", "columns": {"LocationID": {"column_name": "LocationID", "number_non_empty_cells": 89, "number_empty_cells": 0, "number_distinct_values": 5, "frequent_values": [14, 12, 13, 11, 15], "data_types": [{"type": "INTEGER (LONG)", "count": 89, "max_value": 15, "min_value": 11, "mean": 12.865168539325843, "stddev": 1.2912063102538767}]}, "LocationType": {"column_name": "LocationType", "number_non_empty_cells": 89, "number_empty_cells": 0, "number_distinct_values": 1, "frequent_values": ["Off-Street"], "data_types": [{"type": "TEXT", "count": 89, "shortest_values": ["Off-Street"], "longest_values": ["Off-Street"], "average_length": 10.0}]}, "TypeOfTime": {"column_name": "TypeOfTime", "number_non_empty_cells": 89, "number_empty_cells": 0, "number_distinct_values": 2, "frequent_values": ["Weekday", "Weekend"], "data_types": [{"type": "TEXT", "count": 89, "shortest_values": ["Weekday", "Weekend"], "longest_values": ["Weekday", "Weekend"], "average_length": 7.0}]}, "Location": {"column_name": "Location", "number_non_empty_cells": 89, "number_empty_cells": 0, "number_distinct_values": 5, "frequent_values": ["Route 9A Greenway at 80th St.", "Route 9A at 11th St.", "East River Greenway at E90th St.", "East River at E Houston St.", "Route 9A Greenway at 125th St."], "data_types": [{"type": "TEXT", "count": 89, "shortest_values": ["Route 9A at 11th St.", "East River at E Houston St.", "Route 9A Greenway at 80th St.", "Route 9A Greenway at 125th St.", "East River Greenway at E90th St."], "longest_values": ["East River Greenway at E90th St.", "Route 9A Greenway at 125th St.", "Route 9A Greenway at 80th St.", "East River at E Houston St.", "Route 9A at 11th St."], "average_length": 27.382022471910112}]}, "Location_Lat": {"column_name": "Location_Lat", "number_non_empty_cells": 89, "number_empty_cells": 0, "number_distinct_values": 5, "frequent_values": [40.786529, 40.777374, 40.73534, 40.718709, 40.818769], "data_types": [{"type": "INTEGER (LONG)", "count": 89, "max_value": 40, "min_value": 40, "mean": 40.0, "stddev": 0.0}]}, "Location_Long": {"column_name": "Location_Long", "number_non_empty_cells": 89, "number_empty_cells": 0, "number_distinct_values": 5, "frequent_values": [-73.984584, -73.942531, -74.010569, -73.9741, -73.961127], "data_types": [{"type": "INTEGER (LONG)", "count": 89, "max_value": -73, "min_value": -74, "mean": -73.2247191011236, "stddev": 0.4173972049664341}]}, "Year": {"column_name": "Year", "number_non_empty_cells": 89, "number_empty_cells": 0, "number_distinct_values": 11, "frequent_values": [2012, 2015, 2014, 2013, 2010], "data_types": [{"type": "INTEGER (LONG)", "count": 89, "max_value": 2015, "min_value": 2005, "mean": 2010.3932584269662, "stddev": 3.063441471997507}]}, "AllUserVolume": {"column_name": "AllUserVolume", "number_non_empty_cells": 89, "number_empty_cells": 0, "number_distinct_values": 88, "frequent_values": [1170, 1525, 1483, 2776, 4291], "data_types": [{"type": "INTEGER (LONG)", "count": 89, "max_value": 6582, "min_value": 342, "mean": 2593.191011235955, "stddev": 1598.651228389595}]}, "Cyclists_all": {"column_name": "Cyclists_all", "number_non_empty_cells": 89, "number_empty_cells": 0, "number_distinct_values": 85, "frequent_values": [120.0, 197.0, 991.0, 1239.0, 2143.0], "data_types": [{"type": "INTEGER (LONG)", "count": 89, "max_value": 3891, "min_value": 79, "mean": 1196.9213483146068, "stddev": 930.8394933355794}]}, "Cyc_Greenway_only": {"column_name": "Cyc_Greenway_only", "number_non_empty_cells": 89, "number_empty_cells": 0, "number_distinct_values": 85, "frequent_values": [197, 1239, 120, 991, 108], "data_types": [{"type": "INTEGER (LONG)", "count": 89, "max_value": 3875, "min_value": 79, "mean": 1153.4831460674156, "stddev": 951.1994924489007}]}, "Cyc_Helmet_Greenwy": {"column_name": "Cyc_Helmet_Greenwy", "number_non_empty_cells": 89, "number_empty_cells": 0, "number_distinct_values": 86, "frequent_values": [121.0, 155.0, 204.0, 1434.0, 702.0], "data_types": [{"type": "INTEGER (LONG)", "count": 89, "max_value": 2140, "min_value": 15, "mean": 683.5168539325842, "stddev": 565.8547300841813}]}, "Citibike_All": {"column_name": "Citibike_All", "number_non_empty_cells": 89, "number_empty_cells": 0, "number_distinct_values": 23, "frequent_values": [0, 2, 155, 1, 44], "data_types": [{"type": "INTEGER (LONG)", "count": 89, "max_value": 1124, "min_value": 0, "mean": 68.80898876404494, "stddev": 207.77796470230268}]}, "Non_citibikeCyc": {"column_name": "Non_citibikeCyc", "number_non_empty_cells": 89, "number_empty_cells": 0, "number_distinct_values": 85, "frequent_values": [197, 1239, 120, 426, 251], "data_types": [{"type": "INTEGER (LONG)", "count": 89, "max_value": 3292, "min_value": 79, "mean": 1128.112359550562, "stddev": 838.1377623777881}]}, "RllrBld_Scootr": {"column_name": "RllrBld_Scootr", "number_non_empty_cells": 89, "number_empty_cells": 0, "number_distinct_values": 57, "frequent_values": [25.0, 1.0, 8.0, 35.0, 4.0], "data_types": [{"type": "INTEGER (LONG)", "count": 89, "max_value": 315, "min_value": 1, "mean": 39.247191011235955, "stddev": 47.783284393085424}]}, "Jogger": {"column_name": "Jogger", "number_non_empty_cells": 89, "number_empty_cells": 0, "number_distinct_values": 89, "frequent_values": [1395, 243, 1650, 137, 853], "data_types": [{"type": "INTEGER (LONG)", "count": 89, "max_value": 2166, "min_value": 51, "mean": 755.2921348314607, "stddev": 532.9852581861501}]}, "Walker": {"column_name": "Walker", "number_non_empty_cells": 89, "number_empty_cells": 0, "number_distinct_values": 88, "frequent_values": [1001, 115, 540, 623, 101], "data_types": [{"type": "INTEGER (LONG)", "count": 89, "max_value": 1767, "min_value": 44, "mean": 601.7191011235955, "stddev": 362.7105816482909}]}, "CycMaleHel_greenwy": {"column_name": "CycMaleHel_greenwy", "number_non_empty_cells": 36, "number_empty_cells": 53, "number_distinct_values": 37, "frequent_values": [null, 530, 1084, 898, 876], "data_types": [{"type": "INTEGER (LONG)", "count": 36, "max_value": 1465, "min_value": 59, "mean": 554.3333333333334, "stddev": 456.01279221823006}]}, "CycMale_greenwy": {"column_name": "CycMale_greenwy", "number_non_empty_cells": 36, "number_empty_cells": 53, "number_distinct_values": 37, "frequent_values": [null, 1564, 2697, 811, 2022], "data_types": [{"type": "INTEGER (LONG)", "count": 36, "max_value": 2697, "min_value": 131, "mean": 910.3055555555555, "stddev": 753.2235841680168}]}, "CycFemaleHell_greenwy": {"column_name": "CycFemaleHell_greenwy", "number_non_empty_cells": 36, "number_empty_cells": 53, "number_distinct_values": 34, "frequent_values": [null, 59, 161, 33, 501], "data_types": [{"type": "INTEGER (LONG)", "count": 36, "max_value": 675, "min_value": 16, "mean": 228.0, "stddev": 191.61680510852904}]}, "CycFemale_greenwy": {"column_name": "CycFemale_greenwy", "number_non_empty_cells": 36, "number_empty_cells": 53, "number_distinct_values": 37, "frequent_values": [null, 157, 1212, 731, 91], "data_types": [{"type": "INTEGER (LONG)", "count": 36, "max_value": 1212, "min_value": 33, "mean": 374.6111111111111, "stddev": 336.2994100647168}]}, "Cyclists_Male": {"column_name": "Cyclists_Male", "number_non_empty_cells": 36, "number_empty_cells": 53, "number_distinct_values": 37, "frequent_values": [null, 1564, 300, 811, 2675], "data_types": [{"type": "INTEGER (LONG)", "count": 36, "max_value": 2705, "min_value": 131, "mean": 976.5833333333334, "stddev": 717.2732849324432}]}, "Cyclists_Female": {"column_name": "Cyclists_Female", "number_non_empty_cells": 36, "number_empty_cells": 53, "number_distinct_values": 37, "frequent_values": [null, 91, 211, 796, 731], "data_types": [{"type": "INTEGER (LONG)", "count": 36, "max_value": 1216, "min_value": 33, "mean": 400.6388888888889, "stddev": 321.3201201275224}]}}, "key_column_candidates": ["Jogger"], "time_elapsed": 228.39862275123596}