{"dataset_name": "/user/hm74/NYCOpenData/4ynn-w9fk.tsv.gz", "columns": [{"column_name": "DBN", "number_non_empty_cells": 1743, "number_empty_cells": 0, "number_distinct_values": 1743, "frequent_values": ["01M015", "01M019", "01M020", "01M034", "01M063"], "data_type": [{"type": "TEXT", "count": 1743, "shortest_value": ["01M015", "01M019", "01M020", "01M034", "01M063"], "longest_value": ["CITYWIDE", "01M015", "01M019", "01M020", "01M034"], "average_length": 6.001147446930579}]}, {"column_name": "LOCATION NAME", "number_non_empty_cells": 1743, "number_empty_cells": 0, "number_distinct_values": 1706, "frequent_values": ["Home Schooling", "P.S. 360", "P.S. 212", "P.S. 253", "P.S. 015 Roberto Clemente"], "data_type": [{"type": "TEXT", "count": 1743, "shortest_value": ["", "LYFE", "Kappa", "P.S. 89", "Muscota"], "longest_value": ["Collaborative Academy of Science, Technology, & La", "New Explorations into Science, Technology and Math", "47 The American Sign Language and English Secondar", "The Urban Assembly School for Emergency Management", "Stephen T. Mather Building Arts & Craftsmanship Hi"], "average_length": 27.653471026965004}]}, {"column_name": "LOCATION CATEGORY", "number_non_empty_cells": 1743, "number_empty_cells": 0, "number_distinct_values": 11, "frequent_values": ["Elementary", "High school", "Junior High-Intermediate-Middle", "K-8", "Secondary School"], "data_type": [{"type": "TEXT", "count": 1743, "shortest_value": ["", "K-8", "Ungraded", "Elementary", "High school"], "longest_value": ["Junior High-Intermediate-Middle", "District Pre-K Center", "Central-HQ-Citywide", "Secondary School", "K-12 all grades"], "average_length": 13.6815834767642}]}, {"column_name": "ADMINISTRATIVE DISTRICT", "number_non_empty_cells": 1743, "number_empty_cells": 0, "number_distinct_values": 36, "frequent_values": ["2", "10", "9", "31", "75"], "data_type": [{"type": "INTEGER (LONG)", "count": 1742, "max_value": 97, "min_value": 1, "mean": 18.69862227324914, "stddev": 15.635206685981164}, {"type": "TEXT", "count": 1, "shortest_value": [""], "longest_value": [""], "average_length": 0.0}]}, {"column_name": "GEN ED STUDENTS With 2 or More Suspensions or Removals", "number_non_empty_cells": 1743, "number_empty_cells": 0, "number_distinct_values": 35, "frequent_values": ["*", "8", "7", "9", "10"], "data_type": [{"type": "INTEGER (LONG)", "count": 171, "max_value": 5182, "min_value": 6, "mean": 45.25730994152047, "stddev": 394.0596674501112}, {"type": "TEXT", "count": 1572, "shortest_value": ["*"], "longest_value": ["*"], "average_length": 1.0}]}, {"column_name": "SWD STUDENTS With 2 or More Suspensions or Removals", "number_non_empty_cells": 1743, "number_empty_cells": 0, "number_distinct_values": 26, "frequent_values": ["*", "7", "6", "9", "8"], "data_type": [{"type": "INTEGER (LONG)", "count": 171, "max_value": 3957, "min_value": 6, "mean": 34.538011695906434, "stddev": 300.90293458271736}, {"type": "TEXT", "count": 1572, "shortest_value": ["*"], "longest_value": ["*"], "average_length": 1.0}]}, {"column_name": "TOTAL STUDENTS With 2 or More Suspensions or Removals", "number_non_empty_cells": 1743, "number_empty_cells": 0, "number_distinct_values": 53, "frequent_values": ["*", "6", "7", "9", "8"], "data_type": [{"type": "INTEGER (LONG)", "count": 493, "max_value": 9139, "min_value": 6, "mean": 33.973630831643, "stddev": 410.6479781785754}, {"type": "TEXT", "count": 1250, "shortest_value": ["*"], "longest_value": ["*"], "average_length": 1.0}]}], "key_column_candidates": ["DBN"]}