{"dataset_name": "/user/hm74/NYCOpenData/jafx-rvrb.tsv.gz", "columns": [{"column_name": "Project_ID", "number_non_empty_cells": 280, "number_empty_cells": 0, "number_distinct_values": 280, "frequent_values": [51607, 8109, 23267, 59411, 63172], "dataTypes": [{"type": "INTEGER (LONG)", "count": 280, "max_value": 68211, "min_value": 7215, "mean": 48110.899999999994, "stddev": 14775.530484941275}]}, {"column_name": "Project_Name", "number_non_empty_cells": 280, "number_empty_cells": 0, "number_distinct_values": 280, "frequent_values": ["GOTHAM RESIDENTIAL", "625 & 658 DRIGGS AVE", "Frost Street Apartments", "144-146 WEST STREET", "149 Kent Avenue"], "dataTypes": [{"type": "TEXT", "count": 280, "shortest_values": [["THE HUB", 7], ["416 KENT", 8], ["420 Kent", 8], ["QUINCY 15", 9], ["CALADONIA", 9]], "longest_values": [["BFC. 118 ST EDWARDS STREET. INGERSOLL SENIOR RESIDENCES", 55], ["TAPESTRY / EAST 124TH STREET AKA: KINGSGATE HOUSE", 49], ["Greenpoint Landing F2_5 Blue Slip, Brooklyn, NY", 47], ["225 E 39th Street (fka 222 East 40th Street)", 44], ["CARROLL GARDENS- PHASE 2 (363 BOND STREET)", 42]], "average_length": 19.642857142857153}]}, {"column_name": "Administering_Agent", "number_non_empty_cells": 269, "number_empty_cells": 11, "number_distinct_values": 29, "frequent_values": ["Not Available", "HOUSING PARTNERSHIP DEVELOPMENT CORPORATION", "PRATT AREA COMMUNITY COUNCIL INC", "SETTLEMENT HOUSING FUND INC", "Fifth Avenue Committee"], "dataTypes": [{"type": "TEXT", "count": 280, "shortest_values": [["325 KENT LLC", 12], ["Not Available", 13], ["Not Available", 13], ["Not Available", 13], ["Not Available", 13]], "longest_values": [["PHIPPS AFFORDABLE HOUSING ADMINISTERING AGENT CORP.", 51], ["LESPMHA HOUSING DEVELOPMENT FUND CORPORATION", 44], ["HOUSING PARTNERSHIP DEVELOPMENT CORPORATION", 43], ["HOUSING PARTNERSHIP DEVELOPMENT CORPORATION", 43], ["HOUSING PARTNERSHIP DEVELOPMENT CORPORATION", 43]], "average_length": 18.135714285714297}]}, {"column_name": "Project_Status", "number_non_empty_cells": 280, "number_empty_cells": 0, "number_distinct_values": 2, "frequent_values": ["Completed", "In-Construction"], "dataTypes": [{"type": "TEXT", "count": 280, "shortest_values": [["Completed", 9], ["Completed", 9], ["Completed", 9], ["Completed", 9], ["Completed", 9]], "longest_values": [["In-Construction", 15], ["In-Construction", 15], ["In-Construction", 15], ["In-Construction", 15], ["In-Construction", 15]], "average_length": 10.88571428571428}]}, {"column_name": "Total_IH_Floor_Area", "number_non_empty_cells": 280, "number_empty_cells": 0, "number_distinct_values": 279, "frequent_values": [39000.0, 15823.0, 45920.0, 6634.61, 14318.0], "dataTypes": [{"type": "REAL", "count": 280, "max_value": 276874.0, "min_value": 1.0, "mean": 40582.469428571436, "stddev": 42879.64222915748}]}, {"column_name": "Transferred_IH_Floor_Area", "number_non_empty_cells": 280, "number_empty_cells": 0, "number_distinct_values": 248, "frequent_values": [0.0, 14233.0, 9216.0, 47747.4, 6634.61], "dataTypes": [{"type": "REAL", "count": 280, "max_value": 221499.0, "min_value": 0.0, "mean": 31427.66035714282, "stddev": 38592.800675308776}]}, {"column_name": "Remaining_IH_Floor_Area", "number_non_empty_cells": 280, "number_empty_cells": 0, "number_distinct_values": 110, "frequent_values": [0.0, 165.0, 5992.0, 47.12, 7552.0], "dataTypes": [{"type": "REAL", "count": 280, "max_value": 141709.0, "min_value": -2.0, "mean": 5057.334714285713, "stddev": 16820.37472496078}]}]}